medrouter/__init__.py
medrouter/cli.py
medrouter/client.py
medrouter/config.py
medrouter/exceptions.py
medrouter-0.5.0.dist-info/LICENSE
medrouter-0.5.0.dist-info/METADATA
medrouter-0.5.0.dist-info/WHEEL
medrouter-0.5.0.dist-info/entry_points.txt
medrouter-0.5.0.dist-info/top_level.txt
medrouter-0.5.0.dist-info/RECORD
