Metadata-Version: 2.2
Name: medrouter
Version: 0.5.0
Summary: A library for calling different APIs for medical AI usecases.
Home-page: https://github.com/MedRouter/medrouter
Author: PYCAD
Author-email: contact@pycad.co
License: Apache2.0
Project-URL: Source Code, https://github.com/MedRouter/medrouter
Requires-Python: >=3.6
License-File: LICENSE
Requires-Dist: requests
Dynamic: author
Dynamic: author-email
Dynamic: description
Dynamic: description-content-type
Dynamic: home-page
Dynamic: license
Dynamic: project-url
Dynamic: requires-dist
Dynamic: requires-python
Dynamic: summary
